{
  "id": "rss-20260410-005",
  "title": "SymptomWise: A Deterministic Reasoning Layer for Reliable and Efficient AI Systems",
  "source": "rss:arXiv cs.AI",
  "source_url": "https://arxiv.org/abs/2604.06375",
  "author": "arXiv cs.AI",
  "published_at": "2026-04-10T08:42:18.474275+00:00",
  "collected_at": "2026-04-10T08:42:18.474275+00:00",
  "summary": "SymptomWise 提出了一种确定性推理层，旨在提升 AI 系统的可靠性和效率。其核心价值在于通过结构化的推理过程，增强系统在复杂任务中的可预测性和稳健性。",
  "score": 7,
  "tags": [
    "reasoning",
    "deployment",
    "agent"
  ],
  "audience": "intermediate",
  "status": "review",
  "updated_at": "2026-04-10T08:44:55.731338+00:00"
}